{
  "timestamp": "2026-07-15T05:30:39.297Z",
  "players": {
    "Ottomantric": {
      "Overall": {
        "rank": 760289,
        "level": 874,
        "xp": 1410557
      },
      "Attack": {
        "rank": 772341,
        "level": 52,
        "xp": 135496
      },
      "Defence": {
        "rank": 766772,
        "level": 52,
        "xp": 135172
      },
      "Strength": {
        "rank": 806482,
        "level": 52,
        "xp": 136198
      },
      "Constitution": {
        "rank": 844933,
        "level": 52,
        "xp": 135414
      },
      "Ranged": {
        "rank": -1,
        "level": 11,
        "xp": 1508
      },
      "Prayer": {
        "rank": 842294,
        "level": 34,
        "xp": 21567
      },
      "Magic": {
        "rank": 1012896,
        "level": 30,
        "xp": 13435
      },
      "Cooking": {
        "rank": 812967,
        "level": 46,
        "xp": 69030
      },
      "Woodcutting": {
        "rank": 840664,
        "level": 49,
        "xp": 98149
      },
      "Fletching": {
        "rank": 777301,
        "level": 30,
        "xp": 13662
      },
      "Fishing": {
        "rank": 824393,
        "level": 44,
        "xp": 58885
      },
      "Firemaking": {
        "rank": 946226,
        "level": 33,
        "xp": 19204
      },
      "Crafting": {
        "rank": 887554,
        "level": 33,
        "xp": 18533
      },
      "Smithing": {
        "rank": 830986,
        "level": 43,
        "xp": 50385
      },
      "Mining": {
        "rank": 719806,
        "level": 55,
        "xp": 180652
      },
      "Herblore": {
        "rank": -1,
        "level": 5,
        "xp": 449
      },
      "Agility": {
        "rank": 605519,
        "level": 42,
        "xp": 47971
      },
      "Thieving": {
        "rank": 620968,
        "level": 39,
        "xp": 35007
      },
      "Slayer": {
        "rank": -1,
        "level": 11,
        "xp": 1388
      },
      "Farming": {
        "rank": 461934,
        "level": 47,
        "xp": 80309
      },
      "Runecrafting": {
        "rank": -1,
        "level": 7,
        "xp": 686
      },
      "Hunter": {
        "rank": 534564,
        "level": 42,
        "xp": 45851
      },
      "Construction": {
        "rank": 507983,
        "level": 50,
        "xp": 110428
      },
      "Summoning": {
        "rank": -1,
        "level": 1,
        "xp": 0
      },
      "Dungeoneering": {
        "rank": -1,
        "level": 10,
        "xp": 1178
      },
      "Divination": {
        "rank": -1,
        "level": 1,
        "xp": 0
      },
      "Invention": {
        "rank": -1,
        "level": 1,
        "xp": 0
      },
      "Archaeology": {
        "rank": -1,
        "level": 1,
        "xp": 0
      },
      "Necromancy": {
        "rank": -1,
        "level": 1,
        "xp": 0
      }
    },
    "Leihrio": {
      "Overall": {
        "rank": 619771,
        "level": 1196,
        "xp": 4091865
      },
      "Attack": {
        "rank": 1076459,
        "level": 33,
        "xp": 18680
      },
      "Defence": {
        "rank": 631501,
        "level": 63,
        "xp": 385502
      },
      "Strength": {
        "rank": 978794,
        "level": 40,
        "xp": 37421
      },
      "Constitution": {
        "rank": 737033,
        "level": 60,
        "xp": 285644
      },
      "Ranged": {
        "rank": 728842,
        "level": 46,
        "xp": 73421
      },
      "Prayer": {
        "rank": 725646,
        "level": 43,
        "xp": 54776
      },
      "Magic": {
        "rank": 716244,
        "level": 54,
        "xp": 155008
      },
      "Cooking": {
        "rank": 931772,
        "level": 37,
        "xp": 28103
      },
      "Woodcutting": {
        "rank": 860287,
        "level": 47,
        "xp": 82450
      },
      "Fletching": {
        "rank": 709305,
        "level": 40,
        "xp": 38269
      },
      "Fishing": {
        "rank": 923862,
        "level": 35,
        "xp": 23468
      },
      "Firemaking": {
        "rank": 1075097,
        "level": 23,
        "xp": 6590
      },
      "Crafting": {
        "rank": 606487,
        "level": 55,
        "xp": 181472
      },
      "Smithing": {
        "rank": 525056,
        "level": 65,
        "xp": 469623
      },
      "Mining": {
        "rank": 497759,
        "level": 69,
        "xp": 725914
      },
      "Herblore": {
        "rank": -1,
        "level": 14,
        "xp": 2249
      },
      "Agility": {
        "rank": 756502,
        "level": 26,
        "xp": 8997
      },
      "Thieving": {
        "rank": 636699,
        "level": 36,
        "xp": 26994
      },
      "Slayer": {
        "rank": 652276,
        "level": 34,
        "xp": 20258
      },
      "Farming": {
        "rank": 501910,
        "level": 40,
        "xp": 39615
      },
      "Runecrafting": {
        "rank": 621171,
        "level": 41,
        "xp": 43733
      },
      "Hunter": {
        "rank": 630091,
        "level": 23,
        "xp": 6457
      },
      "Construction": {
        "rank": 503457,
        "level": 51,
        "xp": 115420
      },
      "Summoning": {
        "rank": 554612,
        "level": 27,
        "xp": 10444
      },
      "Dungeoneering": {
        "rank": 684217,
        "level": 28,
        "xp": 11105
      },
      "Divination": {
        "rank": 401827,
        "level": 60,
        "xp": 296856
      },
      "Invention": {
        "rank": -1,
        "level": 1,
        "xp": 0
      },
      "Archaeology": {
        "rank": 369273,
        "level": 33,
        "xp": 19251
      },
      "Necromancy": {
        "rank": 215908,
        "level": 72,
        "xp": 924145
      }
    },
    "Qwacker22": {
      "Overall": {
        "rank": 627134,
        "level": 1177,
        "xp": 5687256
      },
      "Attack": {
        "rank": 629735,
        "level": 63,
        "xp": 403101
      },
      "Defence": {
        "rank": 624334,
        "level": 64,
        "xp": 419009
      },
      "Strength": {
        "rank": 663369,
        "level": 63,
        "xp": 390925
      },
      "Constitution": {
        "rank": 691832,
        "level": 63,
        "xp": 393742
      },
      "Ranged": {
        "rank": 912422,
        "level": 30,
        "xp": 13560
      },
      "Prayer": {
        "rank": 859270,
        "level": 33,
        "xp": 18852
      },
      "Magic": {
        "rank": 798278,
        "level": 47,
        "xp": 75434
      },
      "Cooking": {
        "rank": 784227,
        "level": 48,
        "xp": 85819
      },
      "Woodcutting": {
        "rank": 554511,
        "level": 71,
        "xp": 821340
      },
      "Fletching": {
        "rank": 633843,
        "level": 50,
        "xp": 110392
      },
      "Fishing": {
        "rank": 756728,
        "level": 50,
        "xp": 103805
      },
      "Firemaking": {
        "rank": 496496,
        "level": 68,
        "xp": 606289
      },
      "Crafting": {
        "rank": 794837,
        "level": 41,
        "xp": 42800
      },
      "Smithing": {
        "rank": 497053,
        "level": 68,
        "xp": 646689
      },
      "Mining": {
        "rank": 466746,
        "level": 71,
        "xp": 890795
      },
      "Herblore": {
        "rank": -1,
        "level": 1,
        "xp": 36
      },
      "Agility": {
        "rank": 521878,
        "level": 53,
        "xp": 137714
      },
      "Thieving": {
        "rank": 714674,
        "level": 27,
        "xp": 10761
      },
      "Slayer": {
        "rank": 614661,
        "level": 39,
        "xp": 35294
      },
      "Farming": {
        "rank": -1,
        "level": 1,
        "xp": 74
      },
      "Runecrafting": {
        "rank": 818543,
        "level": 21,
        "xp": 5271
      },
      "Hunter": {
        "rank": 650690,
        "level": 19,
        "xp": 4187
      },
      "Construction": {
        "rank": 542166,
        "level": 45,
        "xp": 67855
      },
      "Summoning": {
        "rank": -1,
        "level": 1,
        "xp": 51
      },
      "Dungeoneering": {
        "rank": 526713,
        "level": 47,
        "xp": 78260
      },
      "Divination": {
        "rank": 400020,
        "level": 61,
        "xp": 312975
      },
      "Invention": {
        "rank": -1,
        "level": 1,
        "xp": 0
      },
      "Archaeology": {
        "rank": 384889,
        "level": 28,
        "xp": 11976
      },
      "Necromancy": {
        "rank": -1,
        "level": 3,
        "xp": 250
      }
    },
    "Baz Queefe": {
      "Overall": {
        "rank": 1019758,
        "level": 476,
        "xp": 379265
      },
      "Attack": {
        "rank": 946526,
        "level": 41,
        "xp": 42961
      },
      "Defence": {
        "rank": 932450,
        "level": 42,
        "xp": 46557
      },
      "Strength": {
        "rank": 972769,
        "level": 40,
        "xp": 38185
      },
      "Constitution": {
        "rank": 1015100,
        "level": 41,
        "xp": 44364
      },
      "Ranged": {
        "rank": 1020994,
        "level": 20,
        "xp": 4591
      },
      "Prayer": {
        "rank": 1146405,
        "level": 16,
        "xp": 2925
      },
      "Magic": {
        "rank": 1139356,
        "level": 19,
        "xp": 4151
      },
      "Cooking": {
        "rank": 910443,
        "level": 39,
        "xp": 34225
      },
      "Woodcutting": {
        "rank": 1157507,
        "level": 25,
        "xp": 8630
      },
      "Fletching": {
        "rank": 854488,
        "level": 18,
        "xp": 3763
      },
      "Fishing": {
        "rank": 901031,
        "level": 37,
        "xp": 29946
      },
      "Firemaking": {
        "rank": -1,
        "level": 13,
        "xp": 1840
      },
      "Crafting": {
        "rank": 1044001,
        "level": 16,
        "xp": 2821
      },
      "Smithing": {
        "rank": 852693,
        "level": 41,
        "xp": 44270
      },
      "Mining": {
        "rank": 871373,
        "level": 46,
        "xp": 69205
      },
      "Herblore": {
        "rank": -1,
        "level": 5,
        "xp": 388
      },
      "Agility": {
        "rank": -1,
        "level": 1,
        "xp": 24
      },
      "Thieving": {
        "rank": -1,
        "level": 5,
        "xp": 388
      },
      "Slayer": {
        "rank": -1,
        "level": 1,
        "xp": 0
      },
      "Farming": {
        "rank": -1,
        "level": 1,
        "xp": 0
      },
      "Runecrafting": {
        "rank": -1,
        "level": 1,
        "xp": 0
      },
      "Hunter": {
        "rank": -1,
        "level": 1,
        "xp": 0
      },
      "Construction": {
        "rank": -1,
        "level": 1,
        "xp": 0
      },
      "Summoning": {
        "rank": -1,
        "level": 1,
        "xp": 0
      },
      "Dungeoneering": {
        "rank": -1,
        "level": 1,
        "xp": 0
      },
      "Divination": {
        "rank": -1,
        "level": 1,
        "xp": 31
      },
      "Invention": {
        "rank": -1,
        "level": 1,
        "xp": 0
      },
      "Archaeology": {
        "rank": -1,
        "level": 1,
        "xp": 0
      },
      "Necromancy": {
        "rank": -1,
        "level": 1,
        "xp": 0
      }
    }
  }
}