{
  "timestamp": "2026-07-21T23:00:29.971Z",
  "players": {
    "Ottomantric": {
      "Overall": {
        "rank": 741522,
        "level": 917,
        "xp": 1510619
      },
      "Attack": {
        "rank": 774702,
        "level": 52,
        "xp": 135496
      },
      "Defence": {
        "rank": 769085,
        "level": 52,
        "xp": 135172
      },
      "Strength": {
        "rank": 808835,
        "level": 52,
        "xp": 136198
      },
      "Constitution": {
        "rank": 847327,
        "level": 52,
        "xp": 135414
      },
      "Ranged": {
        "rank": -1,
        "level": 11,
        "xp": 1508
      },
      "Prayer": {
        "rank": 844870,
        "level": 34,
        "xp": 21567
      },
      "Magic": {
        "rank": 1015884,
        "level": 30,
        "xp": 13435
      },
      "Cooking": {
        "rank": 815402,
        "level": 46,
        "xp": 69030
      },
      "Woodcutting": {
        "rank": 820229,
        "level": 51,
        "xp": 112599
      },
      "Fletching": {
        "rank": 779930,
        "level": 30,
        "xp": 13662
      },
      "Fishing": {
        "rank": 827098,
        "level": 44,
        "xp": 58885
      },
      "Firemaking": {
        "rank": 948913,
        "level": 33,
        "xp": 19204
      },
      "Crafting": {
        "rank": 890400,
        "level": 33,
        "xp": 18533
      },
      "Smithing": {
        "rank": 833684,
        "level": 43,
        "xp": 50385
      },
      "Mining": {
        "rank": 722057,
        "level": 55,
        "xp": 180937
      },
      "Herblore": {
        "rank": -1,
        "level": 5,
        "xp": 449
      },
      "Agility": {
        "rank": 607473,
        "level": 42,
        "xp": 47971
      },
      "Thieving": {
        "rank": 623145,
        "level": 39,
        "xp": 35007
      },
      "Slayer": {
        "rank": -1,
        "level": 11,
        "xp": 1388
      },
      "Farming": {
        "rank": 462874,
        "level": 47,
        "xp": 81165
      },
      "Runecrafting": {
        "rank": 570276,
        "level": 48,
        "xp": 85157
      },
      "Hunter": {
        "rank": 536363,
        "level": 42,
        "xp": 45851
      },
      "Construction": {
        "rank": 510034,
        "level": 50,
        "xp": 110428
      },
      "Summoning": {
        "rank": -1,
        "level": 1,
        "xp": 0
      },
      "Dungeoneering": {
        "rank": -1,
        "level": 10,
        "xp": 1178
      },
      "Divination": {
        "rank": -1,
        "level": 1,
        "xp": 0
      },
      "Invention": {
        "rank": -1,
        "level": 1,
        "xp": 0
      },
      "Archaeology": {
        "rank": -1,
        "level": 1,
        "xp": 0
      },
      "Necromancy": {
        "rank": -1,
        "level": 1,
        "xp": 0
      }
    },
    "Leihrio": {
      "Overall": {
        "rank": 579164,
        "level": 1310,
        "xp": 4857345
      },
      "Attack": {
        "rank": 884667,
        "level": 46,
        "xp": 68383
      },
      "Defence": {
        "rank": 604816,
        "level": 66,
        "xp": 533799
      },
      "Strength": {
        "rank": 927720,
        "level": 44,
        "xp": 56071
      },
      "Constitution": {
        "rank": 695895,
        "level": 63,
        "xp": 387586
      },
      "Ranged": {
        "rank": 703172,
        "level": 50,
        "xp": 101829
      },
      "Prayer": {
        "rank": 654308,
        "level": 47,
        "xp": 81242
      },
      "Magic": {
        "rank": 718453,
        "level": 54,
        "xp": 155008
      },
      "Cooking": {
        "rank": 934563,
        "level": 37,
        "xp": 28103
      },
      "Woodcutting": {
        "rank": 826949,
        "level": 50,
        "xp": 107520
      },
      "Fletching": {
        "rank": 709211,
        "level": 40,
        "xp": 39360
      },
      "Fishing": {
        "rank": 922110,
        "level": 35,
        "xp": 24723
      },
      "Firemaking": {
        "rank": 846232,
        "level": 41,
        "xp": 42896
      },
      "Crafting": {
        "rank": 607374,
        "level": 55,
        "xp": 183084
      },
      "Smithing": {
        "rank": 525150,
        "level": 65,
        "xp": 475536
      },
      "Mining": {
        "rank": 499412,
        "level": 69,
        "xp": 726627
      },
      "Herblore": {
        "rank": 665057,
        "level": 27,
        "xp": 9948
      },
      "Agility": {
        "rank": 552645,
        "level": 50,
        "xp": 101616
      },
      "Thieving": {
        "rank": 547842,
        "level": 50,
        "xp": 106216
      },
      "Slayer": {
        "rank": 585226,
        "level": 43,
        "xp": 54962
      },
      "Farming": {
        "rank": 501009,
        "level": 41,
        "xp": 41503
      },
      "Runecrafting": {
        "rank": 623153,
        "level": 41,
        "xp": 43733
      },
      "Hunter": {
        "rank": 632409,
        "level": 23,
        "xp": 6457
      },
      "Construction": {
        "rank": 505476,
        "level": 51,
        "xp": 115420
      },
      "Summoning": {
        "rank": 556362,
        "level": 27,
        "xp": 10444
      },
      "Dungeoneering": {
        "rank": 686436,
        "level": 28,
        "xp": 11105
      },
      "Divination": {
        "rank": 403264,
        "level": 60,
        "xp": 296856
      },
      "Invention": {
        "rank": -1,
        "level": 1,
        "xp": 0
      },
      "Archaeology": {
        "rank": 370832,
        "level": 33,
        "xp": 19251
      },
      "Necromancy": {
        "rank": 214575,
        "level": 73,
        "xp": 1028067
      }
    },
    "Qwacker22": {
      "Overall": {
        "rank": 603461,
        "level": 1244,
        "xp": 7988800
      },
      "Attack": {
        "rank": 572408,
        "level": 70,
        "xp": 753771
      },
      "Defence": {
        "rank": 557939,
        "level": 70,
        "xp": 766679
      },
      "Strength": {
        "rank": 597183,
        "level": 70,
        "xp": 738596
      },
      "Constitution": {
        "rank": 614051,
        "level": 70,
        "xp": 737886
      },
      "Ranged": {
        "rank": 915125,
        "level": 30,
        "xp": 13560
      },
      "Prayer": {
        "rank": 846064,
        "level": 34,
        "xp": 21353
      },
      "Magic": {
        "rank": 794355,
        "level": 47,
        "xp": 79651
      },
      "Cooking": {
        "rank": 774942,
        "level": 49,
        "xp": 94392
      },
      "Woodcutting": {
        "rank": 549955,
        "level": 71,
        "xp": 857290
      },
      "Fletching": {
        "rank": 630720,
        "level": 51,
        "xp": 115455
      },
      "Fishing": {
        "rank": 745659,
        "level": 51,
        "xp": 112418
      },
      "Firemaking": {
        "rank": 497747,
        "level": 68,
        "xp": 606549
      },
      "Crafting": {
        "rank": 796760,
        "level": 41,
        "xp": 42981
      },
      "Smithing": {
        "rank": 460051,
        "level": 71,
        "xp": 885011
      },
      "Mining": {
        "rank": 414513,
        "level": 76,
        "xp": 1350928
      },
      "Herblore": {
        "rank": -1,
        "level": 1,
        "xp": 36
      },
      "Agility": {
        "rank": 494119,
        "level": 56,
        "xp": 201267
      },
      "Thieving": {
        "rank": 675628,
        "level": 32,
        "xp": 16762
      },
      "Slayer": {
        "rank": 607813,
        "level": 40,
        "xp": 40024
      },
      "Farming": {
        "rank": -1,
        "level": 1,
        "xp": 74
      },
      "Runecrafting": {
        "rank": 821108,
        "level": 21,
        "xp": 5271
      },
      "Hunter": {
        "rank": 653070,
        "level": 19,
        "xp": 4187
      },
      "Construction": {
        "rank": 519055,
        "level": 50,
        "xp": 102804
      },
      "Summoning": {
        "rank": -1,
        "level": 5,
        "xp": 433
      },
      "Dungeoneering": {
        "rank": 528530,
        "level": 47,
        "xp": 78260
      },
      "Divination": {
        "rank": 399426,
        "level": 62,
        "xp": 334612
      },
      "Invention": {
        "rank": -1,
        "level": 1,
        "xp": 0
      },
      "Archaeology": {
        "rank": 358563,
        "level": 37,
        "xp": 28300
      },
      "Necromancy": {
        "rank": -1,
        "level": 3,
        "xp": 250
      }
    },
    "Baz Queefe": {
      "Overall": {
        "rank": 1015224,
        "level": 485,
        "xp": 427046
      },
      "Attack": {
        "rank": 948674,
        "level": 41,
        "xp": 43095
      },
      "Defence": {
        "rank": 934929,
        "level": 42,
        "xp": 46690
      },
      "Strength": {
        "rank": 974843,
        "level": 40,
        "xp": 38318
      },
      "Constitution": {
        "rank": 1017510,
        "level": 41,
        "xp": 44496
      },
      "Ranged": {
        "rank": 1024038,
        "level": 20,
        "xp": 4591
      },
      "Prayer": {
        "rank": 1148745,
        "level": 16,
        "xp": 2941
      },
      "Magic": {
        "rank": 1142626,
        "level": 19,
        "xp": 4151
      },
      "Cooking": {
        "rank": 913175,
        "level": 39,
        "xp": 34225
      },
      "Woodcutting": {
        "rank": 1138813,
        "level": 27,
        "xp": 10505
      },
      "Fletching": {
        "rank": 853338,
        "level": 19,
        "xp": 4128
      },
      "Fishing": {
        "rank": 903977,
        "level": 37,
        "xp": 29946
      },
      "Firemaking": {
        "rank": -1,
        "level": 13,
        "xp": 1840
      },
      "Crafting": {
        "rank": 1046303,
        "level": 16,
        "xp": 2865
      },
      "Smithing": {
        "rank": 829441,
        "level": 43,
        "xp": 51618
      },
      "Mining": {
        "rank": 808615,
        "level": 50,
        "xp": 106806
      },
      "Herblore": {
        "rank": -1,
        "level": 5,
        "xp": 388
      },
      "Agility": {
        "rank": -1,
        "level": 1,
        "xp": 24
      },
      "Thieving": {
        "rank": -1,
        "level": 5,
        "xp": 388
      },
      "Slayer": {
        "rank": -1,
        "level": 1,
        "xp": 0
      },
      "Farming": {
        "rank": -1,
        "level": 1,
        "xp": 0
      },
      "Runecrafting": {
        "rank": -1,
        "level": 1,
        "xp": 0
      },
      "Hunter": {
        "rank": -1,
        "level": 1,
        "xp": 0
      },
      "Construction": {
        "rank": -1,
        "level": 1,
        "xp": 0
      },
      "Summoning": {
        "rank": -1,
        "level": 1,
        "xp": 0
      },
      "Dungeoneering": {
        "rank": -1,
        "level": 1,
        "xp": 0
      },
      "Divination": {
        "rank": -1,
        "level": 1,
        "xp": 31
      },
      "Invention": {
        "rank": -1,
        "level": 1,
        "xp": 0
      },
      "Archaeology": {
        "rank": -1,
        "level": 1,
        "xp": 0
      },
      "Necromancy": {
        "rank": -1,
        "level": 1,
        "xp": 0
      }
    }
  }
}